jugmt/__init__.py
jugmt/cli.py
jugmt-1.0.1.dist-info/LICENSE
jugmt-1.0.1.dist-info/METADATA
jugmt-1.0.1.dist-info/WHEEL
jugmt-1.0.1.dist-info/entry_points.txt
jugmt-1.0.1.dist-info/top_level.txt
jugmt-1.0.1.dist-info/RECORD
