Metadata-Version: 2.1
Name: jugmt
Version: 1.0.1
Summary: JUst Give Me Tables
Author-email: "Simon A. F. Lund" <os@safl.dk>
License: LGPL-2.1-only
License-File: LICENSE
Requires-Dist: pytest
Requires-Dist: pytest-cov
Requires-Dist: python-docx
Requires-Dist: senfd
